foilmesh/__init__.py
foilmesh/airfoil.py
foilmesh/connect.py
foilmesh/contourAnalysis.py
foilmesh/controldict.py
foilmesh/elliptic.py
foilmesh/meshing.py
foilmesh/smooth_angle_based.py
foilmesh/splinerefine.py
foilmesh/trailingedge.py
foilmesh/utils.py
foilmesh/meshio/__about__.py
foilmesh/meshio/__init__.py
foilmesh/meshio/_common.py
foilmesh/meshio/_exceptions.py
foilmesh/meshio/_files.py
foilmesh/meshio/_helpers.py
foilmesh/meshio/_mesh.py
foilmesh/meshio/_vtk_common.py
foilmesh/meshio/_cli/__init__.py
foilmesh/meshio/_cli/_ascii.py
foilmesh/meshio/_cli/_binary.py
foilmesh/meshio/_cli/_compress.py
foilmesh/meshio/_cli/_convert.py
foilmesh/meshio/_cli/_decompress.py
foilmesh/meshio/_cli/_info.py
foilmesh/meshio/_cli/_main.py
foilmesh/meshio/_cxml/__init__.py
foilmesh/meshio/_cxml/etree.py
foilmesh/meshio/abaqus/__init__.py
foilmesh/meshio/abaqus/_abaqus.py
foilmesh/meshio/ansys/__init__.py
foilmesh/meshio/ansys/_ansys.py
foilmesh/meshio/avsucd/__init__.py
foilmesh/meshio/avsucd/_avsucd.py
foilmesh/meshio/cgns/__init__.py
foilmesh/meshio/cgns/_cgns.py
foilmesh/meshio/dolfin/__init__.py
foilmesh/meshio/dolfin/_dolfin.py
foilmesh/meshio/exodus/__init__.py
foilmesh/meshio/exodus/_exodus.py
foilmesh/meshio/flac3d/__init__.py
foilmesh/meshio/flac3d/_flac3d.py
foilmesh/meshio/gmsh/__init__.py
foilmesh/meshio/gmsh/_gmsh22.py
foilmesh/meshio/gmsh/_gmsh40.py
foilmesh/meshio/gmsh/_gmsh41.py
foilmesh/meshio/gmsh/common.py
foilmesh/meshio/gmsh/main.py
foilmesh/meshio/h5m/__init__.py
foilmesh/meshio/h5m/_h5m.py
foilmesh/meshio/hmf/__init__.py
foilmesh/meshio/hmf/_hmf.py
foilmesh/meshio/mdpa/__init__.py
foilmesh/meshio/mdpa/_mdpa.py
foilmesh/meshio/med/__init__.py
foilmesh/meshio/med/_med.py
foilmesh/meshio/medit/__init__.py
foilmesh/meshio/medit/_medit.py
foilmesh/meshio/medit/_medit_internal.py
foilmesh/meshio/nastran/__init__.py
foilmesh/meshio/nastran/_nastran.py
foilmesh/meshio/netgen/__init__.py
foilmesh/meshio/netgen/_netgen.py
foilmesh/meshio/neuroglancer/__init__.py
FoilMesh-0.0.8.dist-info/LICENSE.txt
FoilMesh-0.0.8.dist-info/METADATA
FoilMesh-0.0.8.dist-info/WHEEL
FoilMesh-0.0.8.dist-info/top_level.txt
FoilMesh-0.0.8.dist-info/RECORD
