Metadata-Version: 2.1
Name: FoilMesh
Version: 0.0.8
Summary: FoilMesh is a tool to mesh airfoil structural grid
Home-page: https://github.com/Zcaic/Foilmesh
Author: Zcaic
Keywords: aerodynamics cfd airfoil grid mesh
Requires-Python: >=3.0
License-File: LICENSE.txt
Requires-Dist: numpy
Requires-Dist: scipy
Requires-Dist: rich
